README.md
setup.py
decorators/__init__.py
decorators/base.py
decorators/compat.py
decorators/descriptor.py
decorators/misc.py
decorators.egg-info/PKG-INFO
decorators.egg-info/SOURCES.txt
decorators.egg-info/dependency_links.txt
decorators.egg-info/top_level.txt