Metadata-Version: 2.1
Name: decorators
Version: 2.0.5
Summary: Quickly create flexible Python decorators
Home-page: http://github.com/jaymon/decorators
Author: Jay Marcyes
Author-email: jay@marcyes.com
License: MIT
Keywords: decorators decorator @ at-syntax
Platform: UNKNOWN
Classifier: Development Status :: 4 - Beta
Classifier: Environment :: Console
Classifier: Intended Audience :: Developers
Classifier: License :: OSI Approved :: MIT License
Classifier: Operating System :: OS Independent
Classifier: Programming Language :: Python :: 2.7
Classifier: Programming Language :: Python :: 3
